outlier_detection.py
outlier_detection-1.0.6.dist-info/LICENSE
outlier_detection-1.0.6.dist-info/METADATA
outlier_detection-1.0.6.dist-info/WHEEL
outlier_detection-1.0.6.dist-info/license.txt
outlier_detection-1.0.6.dist-info/top_level.txt
outlier_detection-1.0.6.dist-info/RECORD
