Metadata-Version: 2.1
Name: outlier-detection
Version: 1.0.6
Summary: Detect outliers from pandas dataframe using various statistical tools
Home-page: UNKNOWN
License: UNKNOWN
Platform: UNKNOWN
Requires-Dist: seaborn (==0.11.1)
Requires-Dist: matplotlib (==3.2.2)
